pytomorrowio/__init__.py
pytomorrowio/const.py
pytomorrowio/exceptions.py
pytomorrowio/fields.py
pytomorrowio/helpers.py
pytomorrowio/pytomorrowio.py
pytomorrowio-0.3.6.dist-info/AUTHORS.rst
pytomorrowio-0.3.6.dist-info/LICENSE
pytomorrowio-0.3.6.dist-info/METADATA
pytomorrowio-0.3.6.dist-info/WHEEL
pytomorrowio-0.3.6.dist-info/top_level.txt
pytomorrowio-0.3.6.dist-info/RECORD
