Metadata-Version: 2.1
Name: pytomorrowio
Version: 0.3.6
Summary: Async Python3.9+ package to access the Tomorrow.io API
Home-page: https://github.com/raman325/pytomorrowio
Author: raman325
Author-email: 7243222+raman325@users.noreply.github.com
License: MIT license
Keywords: pytomorrowio
Classifier: Development Status :: 2 - Pre-Alpha
Classifier: Intended Audience :: Developers
Classifier: License :: OSI Approved :: MIT License
Classifier: Natural Language :: English
Classifier: Programming Language :: Python :: 3
Classifier: Programming Language :: Python :: 3.9
Classifier: Programming Language :: Python :: 3.10
Requires-Python: >=3.9
License-File: LICENSE
License-File: AUTHORS.rst
